.hgignore
API.rst
LICENSE
MANIFEST.in
README.rst
setup.py
docs/Makefile
docs/conf.py
docs/index.rst
docs/make.bat
json_resource/__init__.py
json_resource/aggregate.py
json_resource/array.py
json_resource/collection.py
json_resource/exceptions.py
json_resource/instance.py
json_resource/mongo.py
json_resource/number.py
json_resource/object.py
json_resource/queryset.py
json_resource/schema.py
json_resource/store.py
json_resource/string.py
json_resource.egg-info/PKG-INFO
json_resource.egg-info/SOURCES.txt
json_resource.egg-info/dependency_links.txt
json_resource.egg-info/requires.txt
json_resource.egg-info/top_level.txt
json_resource/locale/messages.pot
json_resource/locale/nl/LC_MESSAGES/messages.mo
json_resource/locale/nl/LC_MESSAGES/messages.po
json_resource/schemas/schema.json
json_resource/tests/__init__.py
json_resource/tests/test_collection.py
json_resource/tests/test_instance.py
json_resource/tests/test_resource.py
json_resource/tests/test_store.py
json_resource/tests/json/additionalItems.json
json_resource/tests/json/additionalProperties.json
json_resource/tests/json/bignum.json
json_resource/tests/json/dependencies.json
json_resource/tests/json/disallow.json
json_resource/tests/json/divisibleBy.json
json_resource/tests/json/enum.json
json_resource/tests/json/extends.json
json_resource/tests/json/format.json
json_resource/tests/json/items.json
json_resource/tests/json/maxItems.json
json_resource/tests/json/maxLength.json
json_resource/tests/json/maximum.json
json_resource/tests/json/minItems.json
json_resource/tests/json/minLength.json
json_resource/tests/json/minimum.json
json_resource/tests/json/pattern.json
json_resource/tests/json/patternProperties.json
json_resource/tests/json/properties.json
json_resource/tests/json/ref.json
json_resource/tests/json/refRemote.json
json_resource/tests/json/required.json
json_resource/tests/json/type.json
json_resource/tests/json/uniqueItems.json
json_resource/tests/schemas/collection.json
json_resource/tests/schemas/stored-test.json