Metadata-Version: 1.0
Name: json-resource
Version: 0.2.8
Summary: UNKNOWN
Home-page: UNKNOWN
Author: Ernst Odolphi
Author-email: ernst.odolphi@gmail.com
License: UNKNOWN
Platform: UNKNOWN
